zwftools/__init__.py
zwftools/wf_data.py
zwftools/wf_db_hana.py
zwftools/wf_db_mssql.py
zwftools-0.1.3.dist-info/METADATA
zwftools-0.1.3.dist-info/WHEEL
zwftools-0.1.3.dist-info/top_level.txt
zwftools-0.1.3.dist-info/RECORD
