Metadata-Version: 2.4
Name: zwftools
Version: 0.1.3
Requires-Dist: pandas
Requires-Dist: hana_ml
Requires-Dist: sqlalchemy
Dynamic: requires-dist
